pipm/__init__.py
pipm/__main__.py
pipm/src/__init__.py
pipm/src/classes.py
pipm/src/commands.py
pipm/src/file.py
pipm/src/file_utils.py
pipm/src/operations.py
pipm/src/setup_cfg.py
pipm-22.2.3.dist-info/LICENSE
pipm-22.2.3.dist-info/METADATA
pipm-22.2.3.dist-info/WHEEL
pipm-22.2.3.dist-info/entry_points.txt
pipm-22.2.3.dist-info/top_level.txt
pipm-22.2.3.dist-info/RECORD
